[
    {
        "companyName": "Business A",
        "logo": "logo-a.png",
        "phone": "123-456-7890",
        "address": "123 Main Street, City, Country",
        "website": "https://businessA.com",
        "membershipLevel": "Gold"
    },
    {
        "companyName": "Business B",
        "logo": "logo-b.png",
        "phone": "987-654-3210",
        "address": "456 Elm Street, City, Country",
        "website": "https://businessB.com",
        "membershipLevel": "Silver"
    },
    {
        "companyName": "Business C",
        "logo": "logo-c.png",
        "phone": "555-555-5555",
        "address": "789 Oak Street, City, Country",
        "website": "https://businessC.com",
        "membershipLevel": "Gold"
    }
]